shsqlcheck/__init__.py
shsqlcheck/shsqlcheck.py
shsqlcheck-1.0.0.1.dist-info/METADATA
shsqlcheck-1.0.0.1.dist-info/WHEEL
shsqlcheck-1.0.0.1.dist-info/top_level.txt
shsqlcheck-1.0.0.1.dist-info/RECORD
