Metadata-Version: 2.1
Name: shsqlcheck
Version: 1.0.0.1
Summary: Sunghan Database Check
Home-page: https://github.com/choids001/python
Author: SungHan
License: SH
Platform: UNKNOWN
Requires-Python: >=3
